CHANGELOG
INSTALL
MANIFEST.in
README.md
VERSION
setup.cfg
setup.py
badges/__init__.py
badges/apps.py
badges/models.py
badges/tests.py
badges/management/__init__.py
badges/management/commands/__init__.py
badges/management/commands/create_badge_triggers.py
badges/management/commands/trigger.sql
badges/migrations/0001_initial.py
badges/migrations/__init__.py
django_pg_badges.egg-info/PKG-INFO
django_pg_badges.egg-info/SOURCES.txt
django_pg_badges.egg-info/dependency_links.txt
django_pg_badges.egg-info/not-zip-safe
django_pg_badges.egg-info/requires.txt
django_pg_badges.egg-info/top_level.txt