Metadata-Version: 1.1
Name: django-pg-badges
Version: 0.1
Summary: Create badge for your django user with postgresql triggers
Home-page: https://github.com/boblefrag/django-pg-badges
Author: Yohann Gabory
Author-email: boblefrag@gmail.com
License: MIT License
Platform: UNKNOWN
Classifier: Development Status :: 4 - Beta
Classifier: Intended Audience :: Developers
Classifier: License :: OSI Approved :: MIT License
Classifier: Programming Language :: Python
Classifier: Programming Language :: Python :: 2
Classifier: Programming Language :: Python :: 2.7
Classifier: Programming Language :: Python :: 3
Classifier: Programming Language :: Python :: 3.3
Classifier: Programming Language :: Python :: 3.4
